zephyr/__init__.py
zephyr/client/__init__.py
zephyr/client/client.py
zephyr/client/reconnect.py
zephyr/stream/__init__.py
zephyr/stream/stream.py
zephyr/wrapper/__init__.py
zephyr/wrapper/ffmpeg.py
zephyr/wrapper/constants/__init__.py
zephyr/wrapper/constants/bitstream_filter.py
zephyr/wrapper/constants/codec.py
zephyr/wrapper/constants/pixel_format.py
zephyr/wrapper/constants/preset.py
zephyr/wrapper/constants/transport.py
zephyr/wrapper/constants/video_format.py
zephyr_rtsp-0.0.6.dist-info/LICENSE
zephyr_rtsp-0.0.6.dist-info/METADATA
zephyr_rtsp-0.0.6.dist-info/WHEEL
zephyr_rtsp-0.0.6.dist-info/top_level.txt
zephyr_rtsp-0.0.6.dist-info/RECORD
