Metadata-Version: 2.1
Name: zephyr-rtsp
Version: 0.0.6
Summary: A Python library for streaming video over RTSP
Home-page: https://github.com/bpradana/zephyr
Author: Bintang Pradana Erlangga Putra
Author-email: <work.bpradana@gmail.com>
License: MIT
Keywords: python,rtsp,streaming,video
Classifier: Development Status :: 1 - Planning
Classifier: Intended Audience :: Developers
Classifier: Programming Language :: Python :: 3
License-File: LICENSE
Requires-Dist: numpy ==1.26.2
Requires-Dist: opencv-python ==4.8.1.78
Requires-Dist: tenacity ==8.2.3
